proxygetter/__init__.py
proxygetter/blacklist.py
proxygetter/proxy.py
proxygetter/proxy_manager.py
proxygetter/utils.py
proxygetter-0.2.3.dist-info/licenses/LICENSE
tests/__init__.py
tests/test_proxy.py
tests/test_proxy_manager.py
tests/test_utils.py
proxygetter-0.2.3.dist-info/METADATA
proxygetter-0.2.3.dist-info/WHEEL
proxygetter-0.2.3.dist-info/top_level.txt
proxygetter-0.2.3.dist-info/RECORD
