Metadata-Version: 2.4
Name: proxygetter
Version: 0.2.3
Summary: A utility to get and filter free proxies
Home-page: https://github.com/ArthurVerrez/proxygetter
Author: Arthur Verrez
Author-email: macdouglass@outlook.com
Classifier: Development Status :: 3 - Alpha
Classifier: Intended Audience :: Developers
Classifier: License :: OSI Approved :: MIT License
Classifier: Programming Language :: Python :: 3.8
Classifier: Programming Language :: Python :: 3.9
Classifier: Programming Language :: Python :: 3.10
Classifier: Programming Language :: Python :: 3.11
Classifier: Programming Language :: Python :: 3.12
License-File: LICENSE
Requires-Dist: aiohttp==3.9.1
Requires-Dist: aiosignal==1.3.1
Requires-Dist: async-timeout==4.0.3
Requires-Dist: attrs==23.1.0
Requires-Dist: beautifulsoup4==4.12.2
Requires-Dist: certifi==2023.7.22
Requires-Dist: charset-normalizer==3.2.0
Requires-Dist: frozenlist==1.4.0
Requires-Dist: idna==3.4
Requires-Dist: nest-asyncio==1.5.8
Requires-Dist: requests==2.31.0
Requires-Dist: soupsieve==2.5
Requires-Dist: urllib3==2.0.4
Requires-Dist: yarl==1.9.2
Dynamic: author
Dynamic: author-email
Dynamic: classifier
Dynamic: description
Dynamic: description-content-type
Dynamic: home-page
Dynamic: license-file
Dynamic: requires-dist
Dynamic: summary
